{"name":"e2c5ace73ef67e940d47431a7f753e46","link":"#e2c5ace73ef67e940d47431a7f753e46","title":"Chan nho`","description":"Your have the design, your have the code","keywords":"create page, page builder, simple website","blocks":{"a2e497":{"code":"header","style":"style-5","status":1,"order":5,"params":{"logo":{"type":"image","link":"#","value":"Logo-il-light.png"},"menu-button":{"type":"link","class":"btn btn-success btn-sm","text":"Call To Action","link":"#"},"slider":{"type":"list","class":"carousel-inner screen-height","html_tag":"div","control_button":{"class":"carousel-indicators","items_attr":"data-target='#carousel-unique-{{ block-id }}' data-slide-to='{% index %}' class='{% class %}'"},"items":[{"item_class":"active","background-image":{"type":"background","value":"img-slide-1.jpg","class":"section-background background-size-cover col-xs-12","opacity":0.6,"background-position":"center center"},"title":{"value":"The only way to go great work is to love what you do.","type":"text"},"desctiption":{"value":"If you haven't found it yet, keep looking. Don't settle. As with all matters of the heart, you'll know when you find it.","type":"text"},"button-1":{"link":"#button-1","text":"Free Trial","type":"link","class":"btn btn-primary border-radius-extra-xs margin-right-xs-3"},"button-2":{"link":"#button-2","text":"How It Works","type":"link","class":"btn btn-default  btn-line border-radius-extra-xs"}},{"item_class":"","background-image":{"type":"background","value":"img-slide-2.jpg","class":"section-background background-size-cover col-xs-12","opacity":0.6,"background-position":"center center"},"title":{"value":"The only way to go great work is to love what you do.","type":"text"},"desctiption":{"value":"If you haven't found it yet, keep looking. Don't settle. As with all matters of the heart, you'll know when you find it.","type":"text"},"button-1":{"link":"#button-1","text":"Free Trial","type":"link","class":"btn btn-primary border-radius-extra-xs margin-right-xs-3"},"button-2":{"link":"#button-2","text":"How It Works","type":"link","class":"btn btn-default  btn-line border-radius-extra-xs"}}]}}},"ad60a7":{"code":"header","style":"style-7","status":1,"order":7,"params":{"logo":{"type":"image","link":"#","value":"Logo-il-dark.png"},"menu-button":{"type":"link","class":"btn btn-success btn-sm","text":"Call To Action","link":"#"},"slider":{"type":"list","class":"carousel-inner screen-height","html_tag":"div","control_button":{"class":"carousel-indicators","items_attr":"data-target='#carousel-unique-{{ block-id }}' data-slide-to='{% index %}' class='{% class %}'"},"items":[{"item_class":"active","background-image":{"type":"background","value":"image-hero-1.jpg","class":"section-background background-size-cover col-xs-12","opacity":1,"background-position":"center center"},"title":{"value":"We couldn't be prouder of it.","type":"text"},"desctiption":{"value":"Everyone here has the sense that right now is one of those moments when we are influencing the future.","type":"text"},"button":{"link":"#button","text":"View Package","type":"link","class":"btn btn-success border-radius-extra-xs inline-block-xs"}},{"item_class":"","background-image":{"type":"background","value":"image-hero-2.jpg","class":"section-background background-size-cover col-xs-12","opacity":1,"background-position":"center center"},"title":{"value":"We couldn't be prouder of it.","type":"text"},"desctiption":{"value":"Everyone here has the sense that right now is one of those moments when we are influencing the future.","type":"text"},"button":{"link":"#button","text":"View Package","type":"link","class":"btn btn-success border-radius-extra-xs inline-block-xs"}}]}}},"815090":{"code":"header","style":"style-7","status":1,"order":7,"params":{"logo":{"type":"image","link":"#","value":"Logo-il-dark.png"},"menu-button":{"type":"link","class":"btn btn-success btn-sm","text":"Call To Action","link":"#"},"slider":{"type":"list","class":"carousel-inner screen-height","html_tag":"div","control_button":{"class":"carousel-indicators","items_attr":"data-target='#carousel-unique-{{ block-id }}' data-slide-to='{% index %}' class='{% class %}'"},"items":[{"item_class":"active","background-image":{"type":"background","value":"image-hero-1.jpg","class":"section-background background-size-cover col-xs-12","opacity":1,"background-position":"center center"},"title":{"value":"We couldn't be prouder of it.","type":"text"},"desctiption":{"value":"Everyone here has the sense that right now is one of those moments when we are influencing the future.","type":"text"},"button":{"link":"#button","text":"View Package","type":"link","class":"btn btn-success border-radius-extra-xs inline-block-xs"}},{"item_class":"","background-image":{"type":"background","value":"image-hero-2.jpg","class":"section-background background-size-cover col-xs-12","opacity":1,"background-position":"center center"},"title":{"value":"We couldn't be prouder of it.","type":"text"},"desctiption":{"value":"Everyone here has the sense that right now is one of those moments when we are influencing the future.","type":"text"},"button":{"link":"#button","text":"View Package","type":"link","class":"btn btn-success border-radius-extra-xs inline-block-xs"}}]}}}}}